{
  "SerialNumber": "748175D1",
  "TagManufacturerData": "UQgEAAR3S92FKUiQ",
  "MaterialVariantIdentifier": "A01-K1",
  "UniqueMaterialIdentifier": "FA01",
  "FilamentType": "PLA",
  "DetailedFilamentType": "PLA Matte",
  "Color": "000000FF",
  "SpoolWeight": 1000,
  "FilamentDiameter": 1.75,
  "DryingTemperature": 55,
  "DryingTime": 8,
  "BedTemperatureType": 0,
  "BedTemperature": 0,
  "MaxTemperatureForHotend": 230,
  "MinTemperatureForHotend": 190,
  "XCamInfo": "pDiIE+gD6APNzEw/",
  "NozzleDiameter": 0.2,
  "TrayUid": "CBB93F21F9374AA8A9CDFA0AD23647E3",
  "SpoolWidth": 2875,
  "ProductionDateTime": "2024-12-25T13:21:00",
  "ProductionDateTimeShort": "20241225",
  "FilamentLength": 315,
  "FormatIdentifier": 2,
  "ColorCount": 1,
  "SecondColor": "00000000",
  "SkuStart": "A01-K1-1.75-1000"
}