{
  "SerialNumber": "137AE41C",
  "TagManufacturerData": "kQgEAASqyszzXFCQ",
  "MaterialVariantIdentifier": "A00-P5",
  "UniqueMaterialIdentifier": "FA00",
  "FilamentType": "PLA",
  "DetailedFilamentType": "PLA Basic",
  "Color": "5E43B7FF",
  "SpoolWeight": 1000,
  "FilamentDiameter": 1.75,
  "DryingTemperature": 55,
  "DryingTime": 8,
  "BedTemperatureType": 0,
  "BedTemperature": 0,
  "MaxTemperatureForHotend": 230,
  "MinTemperatureForHotend": 190,
  "XCamInfo": "iBOsDegD6AMzMzM/",
  "NozzleDiameter": 0.2,
  "TrayUid": "90A5968E34644FB080B5C3EF6F69E58F",
  "SpoolWidth": 2906,
  "ProductionDateTime": "2025-01-03T14:00:00",
  "ProductionDateTimeShort": "20250103",
  "FilamentLength": 330,
  "FormatIdentifier": 2,
  "ColorCount": 1,
  "SecondColor": "00000000",
  "SkuStart": "A00-P5-1.75-1000"
}