{
  "SerialNumber": "B2D4DE5F",
  "TagManufacturerData": "5wgEAATLl2bdD9KQ",
  "MaterialVariantIdentifier": "A00-G1",
  "UniqueMaterialIdentifier": "FA00",
  "FilamentType": "PLA",
  "DetailedFilamentType": "PLA Basic",
  "Color": "00AE42FF",
  "SpoolWeight": 250,
  "FilamentDiameter": 1.75,
  "DryingTemperature": 55,
  "DryingTime": 8,
  "BedTemperatureType": 1,
  "BedTemperature": 35,
  "MaxTemperatureForHotend": 230,
  "MinTemperatureForHotend": 190,
  "XCamInfo": "iBOIE+gD6AOamRk/",
  "NozzleDiameter": 0.2,
  "TrayUid": "EB3F30AB66964C92B252EBDC0217FC22",
  "SpoolWidth": 6625,
  "ProductionDateTime": "2023-11-15T09:51:00",
  "ProductionDateTimeShort": "23_11_15_09",
  "FilamentLength": 82,
  "FormatIdentifier": 2,
  "ColorCount": 1,
  "SecondColor": "00000000",
  "SkuStart": "A00-G1-1.75-250"
}